{
  "metadata": {
    "filename": "sample_for_analysis.pdf",
    "page_index": 1,
    "page_rect": [
      0.0,
      0.0,
      595.0,
      842.0
    ]
  },
  "get_text_dict": {
    "width": 595.0,
    "height": 842.0,
    "blocks": [
      {
        "number": 0,
        "type": 0,
        "bbox": [
          50.0,
          60.17499923706055,
          189.3919677734375,
          75.28900146484375
        ],
        "lines": [
          {
            "spans": [
              {
                "size": 11.0,
                "flags": 0,
                "bidi": 0,
                "char_flags": 16,
                "font": "Helvetica",
                "color": 0,
                "alpha": 255,
                "ascender": 1.0750000476837158,
                "descender": -0.29899999499320984,
                "text": "This is a standard black text.",
                "origin": [
                  50.0,
                  72.0
                ],
                "bbox": [
                  50.0,
                  60.17499923706055,
                  189.3919677734375,
                  75.28900146484375
                ]
              }
            ],
            "wmode": 0,
            "dir": [
              1.0,
              0.0
            ],
            "bbox": [
              50.0,
              60.17499923706055,
              189.3919677734375,
              75.28900146484375
            ]
          }
        ]
      },
      {
        "number": 1,
        "type": 0,
        "bbox": [
          50.0,
          80.17500305175781,
          133.7539825439453,
          95.28900146484375
        ],
        "lines": [
          {
            "spans": [
              {
                "size": 11.0,
                "flags": 0,
                "bidi": 0,
                "char_flags": 16,
                "font": "Helvetica",
                "color": 16711680,
                "alpha": 255,
                "ascender": 1.0750000476837158,
                "descender": -0.29899999499320984,
                "text": "This is a red text.",
                "origin": [
                  50.0,
                  92.0
                ],
                "bbox": [
                  50.0,
                  80.17500305175781,
                  133.7539825439453,
                  95.28900146484375
                ]
              }
            ],
            "wmode": 0,
            "dir": [
              1.0,
              0.0
            ],
            "bbox": [
              50.0,
              80.17500305175781,
              133.7539825439453,
              95.28900146484375
            ]
          }
        ]
      }
    ]
  },
  "get_text_rawdict": {
    "width": 595.0,
    "height": 842.0,
    "blocks": [
      {
        "number": 0,
        "type": 0,
        "bbox": [
          50.0,
          60.17499923706055,
          189.3919677734375,
          75.28900146484375
        ],
        "lines": [
          {
            "spans": [
              {
                "size": 11.0,
                "flags": 0,
                "bidi": 0,
                "char_flags": 16,
                "font": "Helvetica",
                "color": 0,
                "alpha": 255,
                "ascender": 1.0750000476837158,
                "descender": -0.29899999499320984,
                "chars": [
                  {
                    "origin": [
                      50.0,
                      72.0
                    ],
                    "bbox": [
                      50.0,
                      60.17499923706055,
                      56.72100067138672,
                      75.28900146484375
                    ],
                    "c": "T",
                    "synthetic": false
                  },
                  {
                    "origin": [
                      56.72100067138672,
                      72.0
                    ],
                    "bbox": [
                      56.72100067138672,
                      60.17499923706055,
                      62.83700180053711,
                      75.28900146484375
                    ],
                    "c": "h",
                    "synthetic": false
                  },
                  {
                    "origin": [
                      62.83700180053711,
                      72.0
                    ],
                    "bbox": [
                      62.83700180053711,
                      60.17499923706055,
                      65.27899932861328,
                      75.28900146484375
                    ],
                    "c": "i",
                    "synthetic": false
                  },
                  {
                    "origin": [
                      65.27899932861328,
                      72.0
                    ],
                    "bbox": [
                      65.27899932861328,
                      60.17499923706055,
                      70.77899932861328,
                      75.28900146484375
                    ],
                    "c": "s",
                    "synthetic": false
                  },
                  {
                    "origin": [
                      70.77899932861328,
                      72.0
                    ],
                    "bbox": [
                      70.77899932861328,
                      60.17499923706055,
                      73.83699798583984,
                      75.28900146484375
                    ],
                    "c": " ",
                    "synthetic": false
                  },
                  {
                    "origin": [
                      73.83699798583984,
                      72.0
                    ],
                    "bbox": [
                      73.83699798583984,
                      60.17499923706055,
                      76.27899932861328,
                      75.28900146484375
                    ],
                    "c": "i",
                    "synthetic": false
                  },
                  {
                    "origin": [
                      76.27899932861328,
                      72.0
                    ],
                    "bbox": [
                      76.27899932861328,
                      60.17499923706055,
                      81.77899932861328,
                      75.28900146484375
                    ],
                    "c": "s",
                    "synthetic": false
                  },
                  {
                    "origin": [
                      81.77899932861328,
                      72.0
                    ],
                    "bbox": [
                      81.77899932861328,
                      60.17499923706055,
                      84.83699798583984,
                      75.28900146484375
                    ],
                    "c": " ",
                    "synthetic": false
                  },
                  {
                    "origin": [
                      84.83699798583984,
                      72.0
                    ],
                    "bbox": [
                      84.83699798583984,
                      60.17499923706055,
                      90.95299530029297,
                      75.28900146484375
                    ],
                    "c": "a",
                    "synthetic": false
                  },
                  {
                    "origin": [
                      90.95299530029297,
                      72.0
                    ],
                    "bbox": [
                      90.95299530029297,
                      60.17499923706055,
                      94.01099395751953,
                      75.28900146484375
                    ],
                    "c": " ",
                    "synthetic": false
                  },
                  {
                    "origin": [
                      94.01099395751953,
                      72.0
                    ],
                    "bbox": [
                      94.01099395751953,
                      60.17499923706055,
                      99.51099395751953,
                      75.28900146484375
                    ],
                    "c": "s",
                    "synthetic": false
                  },
                  {
                    "origin": [
                      99.51099395751953,
                      72.0
                    ],
                    "bbox": [
                      99.51099395751953,
                      60.17499923706055,
                      102.5689926147461,
                      75.28900146484375
                    ],
                    "c": "t",
                    "synthetic": false
                  },
                  {
                    "origin": [
                      102.5689926147461,
                      72.0
                    ],
                    "bbox": [
                      102.5689926147461,
                      60.17499923706055,
                      108.68498992919922,
                      75.28900146484375
                    ],
                    "c": "a",
                    "synthetic": false
                  },
                  {
                    "origin": [
                      108.68498992919922,
                      72.0
                    ],
                    "bbox": [
                      108.68498992919922,
                      60.17499923706055,
                      114.80098724365234,
                      75.28900146484375
                    ],
                    "c": "n",
                    "synthetic": false
                  },
                  {
                    "origin": [
                      114.80098724365234,
                      72.0
                    ],
                    "bbox": [
                      114.80098724365234,
                      60.17499923706055,
                      120.91698455810547,
                      75.28900146484375
                    ],
                    "c": "d",
                    "synthetic": false
                  },
                  {
                    "origin": [
                      120.91698455810547,
                      72.0
                    ],
                    "bbox": [
                      120.91698455810547,
                      60.17499923706055,
                      127.0329818725586,
                      75.28900146484375
                    ],
                    "c": "a",
                    "synthetic": false
                  },
                  {
                    "origin": [
                      127.0329818725586,
                      72.0
                    ],
                    "bbox": [
                      127.0329818725586,
                      60.17499923706055,
                      130.69598388671875,
                      75.28900146484375
                    ],
                    "c": "r",
                    "synthetic": false
                  },
                  {
                    "origin": [
                      130.69598388671875,
                      72.0
                    ],
                    "bbox": [
                      130.69598388671875,
                      60.17499923706055,
                      136.81198120117188,
                      75.28900146484375
                    ],
                    "c": "d",
                    "synthetic": false
                  },
                  {
                    "origin": [
                      136.81198120117188,
                      72.0
                    ],
                    "bbox": [
                      136.81198120117188,
                      60.17499923706055,
                      139.86997985839844,
                      75.28900146484375
                    ],
                    "c": " ",
                    "synthetic": false
                  },
                  {
                    "origin": [
                      139.86997985839844,
                      72.0
                    ],
                    "bbox": [
                      139.86997985839844,
                      60.17499923706055,
                      145.98597717285156,
                      75.28900146484375
                    ],
                    "c": "b",
                    "synthetic": false
                  },
                  {
                    "origin": [
                      145.98597717285156,
                      72.0
                    ],
                    "bbox": [
                      145.98597717285156,
                      60.17499923706055,
                      148.427978515625,
                      75.28900146484375
                    ],
                    "c": "l",
                    "synthetic": false
                  },
                  {
                    "origin": [
                      148.427978515625,
                      72.0
                    ],
                    "bbox": [
                      148.427978515625,
                      60.17499923706055,
                      154.54397583007812,
                      75.28900146484375
                    ],
                    "c": "a",
                    "synthetic": false
                  },
                  {
                    "origin": [
                      154.54397583007812,
                      72.0
                    ],
                    "bbox": [
                      154.54397583007812,
                      60.17499923706055,
                      160.04397583007812,
                      75.28900146484375
                    ],
                    "c": "c",
                    "synthetic": false
                  },
                  {
                    "origin": [
                      160.04397583007812,
                      72.0
                    ],
                    "bbox": [
                      160.04397583007812,
                      60.17499923706055,
                      165.54397583007812,
                      75.28900146484375
                    ],
                    "c": "k",
                    "synthetic": false
                  },
                  {
                    "origin": [
                      165.54397583007812,
                      72.0
                    ],
                    "bbox": [
                      165.54397583007812,
                      60.17499923706055,
                      168.6019744873047,
                      75.28900146484375
                    ],
                    "c": " ",
                    "synthetic": false
                  },
                  {
                    "origin": [
                      168.6019744873047,
                      72.0
                    ],
                    "bbox": [
                      168.6019744873047,
                      60.17499923706055,
                      171.65997314453125,
                      75.28900146484375
                    ],
                    "c": "t",
                    "synthetic": false
                  },
                  {
                    "origin": [
                      171.65997314453125,
                      72.0
                    ],
                    "bbox": [
                      171.65997314453125,
                      60.17499923706055,
                      177.77597045898438,
                      75.28900146484375
                    ],
                    "c": "e",
                    "synthetic": false
                  },
                  {
                    "origin": [
                      177.77597045898438,
                      72.0
                    ],
                    "bbox": [
                      177.77597045898438,
                      60.17499923706055,
                      183.27597045898438,
                      75.28900146484375
                    ],
                    "c": "x",
                    "synthetic": false
                  },
                  {
                    "origin": [
                      183.27597045898438,
                      72.0
                    ],
                    "bbox": [
                      183.27597045898438,
                      60.17499923706055,
                      186.33396911621094,
                      75.28900146484375
                    ],
                    "c": "t",
                    "synthetic": false
                  },
                  {
                    "origin": [
                      186.33396911621094,
                      72.0
                    ],
                    "bbox": [
                      186.33396911621094,
                      60.17499923706055,
                      189.3919677734375,
                      75.28900146484375
                    ],
                    "c": ".",
                    "synthetic": false
                  }
                ],
                "origin": [
                  50.0,
                  72.0
                ],
                "bbox": [
                  50.0,
                  60.17499923706055,
                  189.3919677734375,
                  75.28900146484375
                ]
              }
            ],
            "wmode": 0,
            "dir": [
              1.0,
              0.0
            ],
            "bbox": [
              50.0,
              60.17499923706055,
              189.3919677734375,
              75.28900146484375
            ]
          }
        ]
      },
      {
        "number": 1,
        "type": 0,
        "bbox": [
          50.0,
          80.17500305175781,
          133.7539825439453,
          95.28900146484375
        ],
        "lines": [
          {
            "spans": [
              {
                "size": 11.0,
                "flags": 0,
                "bidi": 0,
                "char_flags": 16,
                "font": "Helvetica",
                "color": 16711680,
                "alpha": 255,
                "ascender": 1.0750000476837158,
                "descender": -0.29899999499320984,
                "chars": [
                  {
                    "origin": [
                      50.0,
                      92.0
                    ],
                    "bbox": [
                      50.0,
                      80.17500305175781,
                      56.72100067138672,
                      95.28900146484375
                    ],
                    "c": "T",
                    "synthetic": false
                  },
                  {
                    "origin": [
                      56.72100067138672,
                      92.0
                    ],
                    "bbox": [
                      56.72100067138672,
                      80.17500305175781,
                      62.83700180053711,
                      95.28900146484375
                    ],
                    "c": "h",
                    "synthetic": false
                  },
                  {
                    "origin": [
                      62.83700180053711,
                      92.0
                    ],
                    "bbox": [
                      62.83700180053711,
                      80.17500305175781,
                      65.27899932861328,
                      95.28900146484375
                    ],
                    "c": "i",
                    "synthetic": false
                  },
                  {
                    "origin": [
                      65.27899932861328,
                      92.0
                    ],
                    "bbox": [
                      65.27899932861328,
                      80.17500305175781,
                      70.77899932861328,
                      95.28900146484375
                    ],
                    "c": "s",
                    "synthetic": false
                  },
                  {
                    "origin": [
                      70.77899932861328,
                      92.0
                    ],
                    "bbox": [
                      70.77899932861328,
                      80.17500305175781,
                      73.83699798583984,
                      95.28900146484375
                    ],
                    "c": " ",
                    "synthetic": false
                  },
                  {
                    "origin": [
                      73.83699798583984,
                      92.0
                    ],
                    "bbox": [
                      73.83699798583984,
                      80.17500305175781,
                      76.27899932861328,
                      95.28900146484375
                    ],
                    "c": "i",
                    "synthetic": false
                  },
                  {
                    "origin": [
                      76.27899932861328,
                      92.0
                    ],
                    "bbox": [
                      76.27899932861328,
                      80.17500305175781,
                      81.77899932861328,
                      95.28900146484375
                    ],
                    "c": "s",
                    "synthetic": false
                  },
                  {
                    "origin": [
                      81.77899932861328,
                      92.0
                    ],
                    "bbox": [
                      81.77899932861328,
                      80.17500305175781,
                      84.83699798583984,
                      95.28900146484375
                    ],
                    "c": " ",
                    "synthetic": false
                  },
                  {
                    "origin": [
                      84.83699798583984,
                      92.0
                    ],
                    "bbox": [
                      84.83699798583984,
                      80.17500305175781,
                      90.95299530029297,
                      95.28900146484375
                    ],
                    "c": "a",
                    "synthetic": false
                  },
                  {
                    "origin": [
                      90.95299530029297,
                      92.0
                    ],
                    "bbox": [
                      90.95299530029297,
                      80.17500305175781,
                      94.01099395751953,
                      95.28900146484375
                    ],
                    "c": " ",
                    "synthetic": false
                  },
                  {
                    "origin": [
                      94.01099395751953,
                      92.0
                    ],
                    "bbox": [
                      94.01099395751953,
                      80.17500305175781,
                      97.67399597167969,
                      95.28900146484375
                    ],
                    "c": "r",
                    "synthetic": false
                  },
                  {
                    "origin": [
                      97.67399597167969,
                      92.0
                    ],
                    "bbox": [
                      97.67399597167969,
                      80.17500305175781,
                      103.78999328613281,
                      95.28900146484375
                    ],
                    "c": "e",
                    "synthetic": false
                  },
                  {
                    "origin": [
                      103.78999328613281,
                      92.0
                    ],
                    "bbox": [
                      103.78999328613281,
                      80.17500305175781,
                      109.90599060058594,
                      95.28900146484375
                    ],
                    "c": "d",
                    "synthetic": false
                  },
                  {
                    "origin": [
                      109.90599060058594,
                      92.0
                    ],
                    "bbox": [
                      109.90599060058594,
                      80.17500305175781,
                      112.9639892578125,
                      95.28900146484375
                    ],
                    "c": " ",
                    "synthetic": false
                  },
                  {
                    "origin": [
                      112.9639892578125,
                      92.0
                    ],
                    "bbox": [
                      112.9639892578125,
                      80.17500305175781,
                      116.02198791503906,
                      95.28900146484375
                    ],
                    "c": "t",
                    "synthetic": false
                  },
                  {
                    "origin": [
                      116.02198791503906,
                      92.0
                    ],
                    "bbox": [
                      116.02198791503906,
                      80.17500305175781,
                      122.13798522949219,
                      95.28900146484375
                    ],
                    "c": "e",
                    "synthetic": false
                  },
                  {
                    "origin": [
                      122.13798522949219,
                      92.0
                    ],
                    "bbox": [
                      122.13798522949219,
                      80.17500305175781,
                      127.63798522949219,
                      95.28900146484375
                    ],
                    "c": "x",
                    "synthetic": false
                  },
                  {
                    "origin": [
                      127.63798522949219,
                      92.0
                    ],
                    "bbox": [
                      127.63798522949219,
                      80.17500305175781,
                      130.69598388671875,
                      95.28900146484375
                    ],
                    "c": "t",
                    "synthetic": false
                  },
                  {
                    "origin": [
                      130.69598388671875,
                      92.0
                    ],
                    "bbox": [
                      130.69598388671875,
                      80.17500305175781,
                      133.7539825439453,
                      95.28900146484375
                    ],
                    "c": ".",
                    "synthetic": false
                  }
                ],
                "origin": [
                  50.0,
                  92.0
                ],
                "bbox": [
                  50.0,
                  80.17500305175781,
                  133.7539825439453,
                  95.28900146484375
                ]
              }
            ],
            "wmode": 0,
            "dir": [
              1.0,
              0.0
            ],
            "bbox": [
              50.0,
              80.17500305175781,
              133.7539825439453,
              95.28900146484375
            ]
          }
        ]
      }
    ]
  },
  "get_drawings": [
    {
      "items": [
        [
          "re",
          [
            50.0,
            110.0,
            250.0,
            140.0
          ],
          1
        ]
      ],
      "type": "fs",
      "even_odd": false,
      "fill_opacity": 1.0,
      "fill": [
        0.0,
        1.0,
        0.0
      ],
      "rect": [
        50.0,
        110.0,
        250.0,
        140.0
      ],
      "seqno": 2,
      "layer": "",
      "stroke_opacity": 1.0,
      "color": [
        0.0,
        0.0,
        1.0
      ],
      "width": 1.5,
      "lineCap": [
        0,
        0,
        0
      ],
      "lineJoin": 0.0,
      "closePath": false,
      "dashes": "[] 0"
    }
  ],
  "get_images_full": [],
  "get_links": [
    {
      "kind": 2,
      "xref": 9,
      "from": [
        50.0,
        72.0,
        200.0,
        82.0
      ],
      "uri": "https://example.com",
      "id": "fitz-L0"
    }
  ]
}